ai/__init__.py
ai/environments/__init__.py
ai/environments/_base.py
ai/environments/_factory.py
ai/environments/_gym_wrapper.py
ai/environments/_simulator_wrapper.py
ai/environments/action_spaces/__init__.py
ai/environments/action_spaces/_base.py
ai/environments/action_spaces/_discrete.py
ai/rl/__init__.py
ai/rl/_ppo/__init__.py
ai/rl/a3c/__init__.py
ai/rl/a3c/_agent.py
ai/rl/a3c/trainer/__init__.py
ai/rl/a3c/trainer/_config.py
ai/rl/a3c/trainer/_logger.py
ai/rl/a3c/trainer/_trainer.py
ai/rl/a3c/trainer/_worker.py
ai/rl/alpha_zero/__init__.py
ai/rl/alpha_zero/_train.py
ai/rl/alpha_zero/_core/__init__.py
ai/rl/alpha_zero/_core/learner_worker.py
ai/rl/alpha_zero/_core/logger.py
ai/rl/alpha_zero/_core/mcts.py
ai/rl/alpha_zero/_core/mcts_node.py
ai/rl/alpha_zero/_core/self_play_worker.py
ai/rl/alpha_zero/networks/__init__.py
ai/rl/alpha_zero/networks/_connect_four.py
ai/rl/alpha_zero/networks/_tictactoe.py
ai/rl/dqn/__init__.py
ai/rl/dqn/rainbow/__init__.py
ai/rl/dqn/rainbow/_agent.py
ai/rl/dqn/rainbow/_agent_config.py
ai/rl/dqn/rainbow/networks/__init__.py
ai/rl/dqn/rainbow/networks/_cart_pole.py
ai/rl/dqn/rainbow/trainers/__init__.py
ai/rl/dqn/rainbow/trainers/basic/__init__.py
ai/rl/dqn/rainbow/trainers/basic/_config.py
ai/rl/dqn/rainbow/trainers/basic/_trainer.py
ai/rl/dqn/rainbow/trainers/seed/__init__.py
ai/rl/dqn/rainbow/trainers/seed/_actor.py
ai/rl/dqn/rainbow/trainers/seed/_config.py
ai/rl/dqn/rainbow/trainers/seed/_trainer.py
ai/rl/utils/__init__.py
ai/rl/utils/_n_step_reward_collector.py
ai/rl/utils/buffers/__init__.py
ai/rl/utils/buffers/_base.py
ai/rl/utils/buffers/_uniform.py
ai/rl/utils/buffers/_weighted.py
ai/rl/utils/seed/__init__.py
ai/rl/utils/seed/_broadcaster.py
ai/rl/utils/seed/_inference_client.py
ai/rl/utils/seed/_inference_proxy.py
ai/rl/utils/seed/_inference_server.py
ai/search/__init__.py
ai/search/minimax/__init__.py
ai/search/minimax/_heuristic.py
ai/search/minimax/_minimax.py
ai/simulators/__init__.py
ai/simulators/_base.py
ai_projects-0.0.9.dist-info/METADATA
ai_projects-0.0.9.dist-info/WHEEL
ai_projects-0.0.9.dist-info/top_level.txt
ai_projects-0.0.9.dist-info/RECORD
